flask_apiy/__init__.py
flask_apiy/utils.py
flask_apiy-0.3.1.dist-info/METADATA
flask_apiy-0.3.1.dist-info/RECORD
flask_apiy-0.3.1.dist-info/WHEEL
flask_apiy-0.3.1.dist-info/top_level.txt
